mseep_mcp_ynu-0.1.2.dist-info/licenses/LICENSE
prompts/__init__.py
prompts/example.py
resources/__init__.py
resources/example.py
tests/__init__.py
tests/test_rs_staff.py
tools/__init__.py
tools/example.py
tools/rs_staff.py
mseep_mcp_ynu-0.1.2.dist-info/METADATA
mseep_mcp_ynu-0.1.2.dist-info/WHEEL
mseep_mcp_ynu-0.1.2.dist-info/top_level.txt
mseep_mcp_ynu-0.1.2.dist-info/RECORD
